package_riddhi/__init__.py
package_riddhi/api_dealer.py
package_riddhi-0.1.dist-info/METADATA
package_riddhi-0.1.dist-info/WHEEL
package_riddhi-0.1.dist-info/top_level.txt
package_riddhi-0.1.dist-info/RECORD
